filur/main.py
filur/models/__init__.py
filur/models/file.py
filur/models/pattern.py
filur/schemas/__init__.py
filur/schemas/configuration.py
filur/templates/template.html
filur-0.1.1.dist-info/METADATA
filur-0.1.1.dist-info/WHEEL
filur-0.1.1.dist-info/entry_points.txt
filur-0.1.1.dist-info/licenses/LICENSE
filur-0.1.1.dist-info/RECORD
