Metadata-Version: 2.4
Name: filur
Version: 0.1.1
Summary: A tiny lil' log searcher
Project-URL: Homepage, https://github.com/kverqus/filur
Project-URL: Issues, https://github.com/kverqus/filur/issues
Author-email: Kristoffer Nilsson <kristoffer@kverqus.se>
License-File: LICENSE
Classifier: License :: OSI Approved :: MIT License
Classifier: Operating System :: OS Independent
Classifier: Programming Language :: Python :: 3
Requires-Python: >=3.10
Requires-Dist: jinja2==3.1.4
Requires-Dist: markupsafe==3.0.2
Requires-Dist: pyyaml==6.0.2
Requires-Dist: schema==0.7.7
